[
  {
    "word": "Bank",
    "phonetic": "/bæŋk/",
    "definition": "银行",
    "example": "I need to go to the bank to deposit a check.",
    "example_trans": "我需要去银行存一张支票。",
    "derivatives": ["banking (n.)"],
    "tags": ["基础词汇", "金融"],
    "categories": ["银行"],
    "level": 1
  },
  {
    "word": "Account",
    "phonetic": "/əˈkaʊnt/",
    "definition": "账户",
    "example": "I have a savings account and a checking account.",
    "example_trans": "我有一个储蓄账户和一个支票账户。",
    "derivatives": ["accountant (n.)"],
    "tags": ["常用", "金融"],
    "categories": ["银行"],
    "level": 1
  },
  {
    "word": "Deposit",
    "phonetic": "/dɪˈpɑːzɪt/",
    "definition": "存款",
    "example": "I want to deposit this check into my account.",
    "example_trans": "我想把这张支票存入我的账户。",
    "derivatives": [],
    "tags": ["常用", "交易"],
    "categories": ["银行"],
    "level": 1
  },
  {
    "word": "Withdraw",
    "phonetic": "/wɪðˈdrɔː/",
    "definition": "取款",
    "example": "I need to withdraw some cash from the ATM.",
    "example_trans": "我需要从自动取款机取一些现金。",
    "derivatives": ["withdrawal (n.)"],
    "tags": ["常用", "交易"],
    "categories": ["银行"],
    "level": 1
  },
  {
    "word": "Balance",
    "phonetic": "/ˈbæləns/",
    "definition": "余额",
    "example": "I checked my account balance online.",
    "example_trans": "我在网上查了我的账户余额。",
    "derivatives": [],
    "tags": ["常用", "金融"],
    "categories": ["银行"],
    "level": 1
  },
  {
    "word": "Loan",
    "phonetic": "/loʊn/",
    "definition": "贷款",
    "example": "I took out a loan to buy a car.",
    "example_trans": "我贷款买了一辆车。",
    "derivatives": ["lend (v.)"],
    "tags": ["常用", "金融"],
    "categories": ["银行"],
    "level": 1
  },
  {
    "word": "Interest",
    "phonetic": "/ˈɪntrəst/",
    "definition": "利息",
    "example": "The interest rate on my savings account is low.",
    "example_trans": "我的储蓄账户的利率很低。",
    "derivatives": [],
    "tags": ["常用", "金融"],
    "categories": ["银行"],
    "level": 1
  },
  {
    "word": "ATM",
    "phonetic": "/ˌeɪ tiː ˈem/",
    "definition": "自动取款机",
    "example": "I used the ATM to get cash.",
    "example_trans": "我用自动取款机取了现金。",
    "derivatives": [],
    "tags": ["常用", "机器"],
    "categories": ["银行"],
    "level": 1
  },
  {
    "word": "Teller",
    "phonetic": "/ˈtelər/",
    "definition": "银行柜员",
    "example": "I spoke to the teller about opening a new account.",
    "example_trans": "我和银行柜员谈了开新账户的事情。",
    "derivatives": [],
    "tags": ["常用", "人员"],
    "categories": ["银行"],
    "level": 1
  },
  {
    "word": "Check",
    "phonetic": "/tʃek/",
    "definition": "支票",
    "example": "I wrote a check to pay the bill.",
    "example_trans": "我写了一张支票来支付账单。",
    "derivatives": [],
    "tags": ["常用", "支付"],
    "categories": ["银行"],
    "level": 1
  },
  {
    "word": "Credit card",
    "phonetic": "/ˈkredɪt kɑːrd/",
    "definition": "信用卡",
    "example": "I paid with my credit card.",
    "example_trans": "我用信用卡支付。",
    "derivatives": [],
    "tags": ["常用", "支付"],
    "categories": ["银行"],
    "level": 1
  },
  {
    "word": "Debit card",
    "phonetic": "/ˈdebɪt kɑːrd/",
    "definition": "借记卡",
    "example": "I used my debit card to buy groceries.",
    "example_trans": "我用借记卡买了杂货。",
    "derivatives": [],
    "tags": ["常用", "支付"],
    "categories": ["银行"],
    "level": 1
  },
  {
    "word": "PIN",
    "phonetic": "/pɪn/",
    "definition": "密码",
    "example": "Enter your PIN to access your account.",
    "example_trans": "输入你的密码以访问你的账户。",
    "derivatives": [],
    "tags": ["安全", "密码"],
    "categories": ["银行"],
    "level": 1
  },
  {
    "word": "Transaction",
    "phonetic": "/trænˈzækʃən/",
    "definition": "交易",
    "example": "I reviewed my recent transactions online.",
    "example_trans": "我在网上查看了我最近的交易记录。",
    "derivatives": [],
    "tags": ["常用", "记录"],
    "categories": ["银行"],
    "level": 1
  },
  {
    "word": "Statement",
    "phonetic": "/ˈsteɪtmənt/",
    "definition": "账单；报表",
    "example": "I received my bank statement in the mail.",
    "example_trans": "我收到了邮寄的银行账单。",
    "derivatives": [],
    "tags": ["常用", "记录"],
    "categories": ["银行"],
    "level": 1
  },
  {
    "word": "Overdraft",
    "phonetic": "/ˈoʊvərdræft/",
    "definition": "透支",
    "example": "I was charged an overdraft fee.",
    "example_trans": "我被收取了透支费。",
    "derivatives": [],
    "tags": ["费用", "金融"],
    "categories": ["银行"],
    "level": 2
  },
  {
    "word": "Fee",
    "phonetic": "/fiː/",
    "definition": "费用",
    "example": "The bank charges a monthly fee for the account.",
    "example_trans": "银行对该账户收取月费。",
    "derivatives": [],
    "tags": ["常用", "费用"],
    "categories": ["银行"],
    "level": 1
  },
  {
    "word": "Mortgage",
    "phonetic": "/ˈmɔːrɡɪdʒ/",
    "definition": "抵押贷款",
    "example": "We have a mortgage on our house.",
    "example_trans": "我们有房屋抵押贷款。",
    "derivatives": [],
    "tags": ["常用", "金融"],
    "categories": ["银行"],
    "level": 1
  },
  {
    "word": "Currency",
    "phonetic": "/ˈkɜːrənsi/",
    "definition": "货币",
    "example": "What currency do you need?",
    "example_trans": "你需要什么货币？",
    "derivatives": [],
    "tags": ["常用", "金融"],
    "categories": ["银行"],
    "level": 1
  },
  {
    "word": "Exchange rate",
    "phonetic": "/ɪksˈtʃeɪndʒ reɪt/",
    "definition": "汇率",
    "example": "The exchange rate between the dollar and the euro fluctuates.",
    "example_trans": "美元和欧元之间的汇率波动。",
    "derivatives": [],
    "tags": ["常用", "金融"],
    "categories": ["银行"],
    "level": 2
  },
  {
    "word": "Wire transfer",
    "phonetic": "/ˈwaɪər trænsfɜːr/",
    "definition": "电汇",
    "example": "I need to send a wire transfer to another country.",
    "example_trans": "我需要向另一个国家汇款。",
    "derivatives": [],
    "tags": ["常用", "交易"],
    "categories": ["银行"],
    "level": 2
  },
  {
    "word": "Online banking",
    "phonetic": "/ˌɒnˈlaɪn ˈbæŋkɪŋ/",
    "definition": "网上银行",
    "example": "I use online banking to pay my bills.",
    "example_trans": "我使用网上银行支付账单。",
    "derivatives": [],
    "tags": ["常用", "科技"],
    "categories": ["银行"],
    "level": 1
  },
  {
    "word": "Mobile banking",
    "phonetic": "/ˈmoʊbaɪl ˈbæŋkɪŋ/",
    "definition": "手机银行",
    "example": "I can check my balance using mobile banking.",
    "example_trans": "我可以使用手机银行查看我的余额。",
    "derivatives": [],
    "tags": ["常用", "科技"],
    "categories": ["银行"],
    "level": 1
  },
  {
    "word": "Branch",
    "phonetic": "/bræntʃ/",
    "definition": "银行分行",
    "example": "The bank has many branches in the city.",
    "example_trans": "这家银行在城市里有很多分行。",
    "derivatives": [],
    "tags": ["常用", "地点"],
    "categories": ["银行"],
    "level": 1
  },
  {
    "word": "Safe deposit box",
    "phonetic": "/seɪf dɪˈpɑːzɪt bɑːks/",
    "definition": "保险箱",
    "example": "I keep important documents in a safe deposit box.",
    "example_trans": "我把重要的文件放在保险箱里。",
    "derivatives": [],
    "tags": ["安全", "储存"],
    "categories": ["银行"],
    "level": 2
  },
  {
    "word": "Credit score",
    "phonetic": "/ˈkredɪt skɔːr/",
    "definition": "信用评分",
    "example": "A good credit score is important for getting a loan.",
    "example_trans": "良好的信用评分对于获得贷款很重要。",
    "derivatives": [],
    "tags": ["金融", "信用"],
    "categories": ["银行"],
    "level": 2
  },
  {
    "word": "Identity theft",
    "phonetic": "/aɪˈdentəti θeft/",
    "definition": "身份盗窃",
    "example": "I'm worried about identity theft.",
    "example_trans": "我担心身份盗窃。",
    "derivatives": [],
    "tags": ["安全", "犯罪"],
    "categories": ["银行"],
    "level": 2
  },
  {
    "word": "Fraud",
    "phonetic": "/frɔːd/",
    "definition": "欺诈",
    "example": "Report any suspected fraud to the bank.",
    "example_trans": "向银行报告任何可疑的欺诈行为。",
    "derivatives": ["fraudulent (adj.)"],
    "tags": ["安全", "犯罪"],
    "categories": ["银行"],
    "level": 2
  },
  {
    "word": "Money laundering",
    "phonetic": "/ˈmʌni ˈlɔːndərɪŋ/",
    "definition": "洗钱",
    "example": "The bank is investigating money laundering.",
    "example_trans": "银行正在调查洗钱行为。",
    "derivatives": [],
    "tags": ["犯罪", "金融"],
    "categories": ["银行"],
    "level": 3
  },
  {
    "word": "Collateral",
    "phonetic": "/kəˈlætərəl/",
    "definition": "抵押品",
    "example": "The bank requires collateral for the loan.",
    "example_trans": "银行要求贷款提供抵押品。",
    "derivatives": [],
    "tags": ["金融", "安全"],
    "categories": ["银行"],
    "level": 2
  },
  {
    "word": "Bankruptcy",
    "phonetic": "/ˈbæŋkrʌptsi/",
    "definition": "破产",
    "example": "The company filed for bankruptcy.",
    "example_trans": "该公司申请破产。",
    "derivatives": ["bankrupt (adj.)"],
    "tags": ["金融", "风险"],
    "categories": ["银行"],
    "level": 2
  },
  {
    "word": "Investment",
    "phonetic": "/ɪnˈvestmənt/",
    "definition": "投资",
    "example": "I made an investment in the stock market.",
    "example_trans": "我在股市上做了一项投资。",
    "derivatives": ["invest (v.)"],
    "tags": ["金融", "理财"],
    "categories": ["银行"],
    "level": 2
  },
  {
    "word": "Savings account",
    "phonetic": "/ˈseɪvɪŋz əˈkaʊnt/",
    "definition": "储蓄账户",
    "example": "I have a savings account for emergencies.",
    "example_trans": "我有一个储蓄账户用于紧急情况。",
    "derivatives": [],
    "tags": ["常用", "账户"],
    "categories": ["银行"],
    "level": 1
  },
  {
    "word": "Checking account",
    "phonetic": "/ˈtʃekɪŋ əˈkaʊnt/",
    "definition": "支票账户",
    "example": "I use my checking account to pay bills.",
    "example_trans": "我用我的支票账户支付账单。",
    "derivatives": [],
    "tags": ["常用", "账户"],
    "categories": ["银行"],
    "level": 1
  },
  {
    "word": "Money market account",
    "phonetic": "/ˈmʌni ˈmɑːrkɪt əˈkaʊnt/",
    "definition": "货币市场账户",
    "example": "A money market account offers higher interest rates.",
    "example_trans": "货币市场账户提供更高的利率。",
    "derivatives": [],
    "tags": ["金融", "账户"],
    "categories": ["银行"],
    "level": 2
  },
  {
    "word": "Certificate of deposit (CD)",
    "phonetic": "/sərˈtɪfɪkət əv dɪˈpɑːzɪt/",
    "definition": "定期存款",
    "example": "I invested in a certificate of deposit.",
    "example_trans": "我投资了定期存款。",
    "derivatives": [],
    "tags": ["金融", "账户"],
    "categories": ["银行"],
    "level": 2
  },
  {
    "word": "Overdraft protection",
    "phonetic": "/ˈoʊvərdræft prəˈtekʃən/",
    "definition": "透支保护",
    "example": "I have overdraft protection on my account.",
    "example_trans": "我的账户有透支保护。",
    "derivatives": [],
    "tags": ["金融", "服务"],
    "categories": ["银行"],
    "level": 2
  },
  {
    "word": "Direct deposit",
    "phonetic": "/daɪˈrekt dɪˈpɑːzɪt/",
    "definition": "直接存款",
    "example": "I receive my paycheck through direct deposit.",
    "example_trans": "我通过直接存款收到我的工资。",
    "derivatives": [],
    "tags": ["常用", "服务"],
    "categories": ["银行"],
    "level": 1
  },
  {
    "word": "Automatic payment",
    "phonetic": "/ˌɔːtəˈmætɪk ˈpeɪmənt/",
    "definition": "自动付款",
    "example": "I set up automatic payments for my bills.",
    "example_trans": "我设置了账单自动付款。",
    "derivatives": [],
    "tags": ["常用", "服务"],
    "categories": ["银行"],
    "level": 1
  },
  {
    "word": "Safe",
    "phonetic": "/seɪf/",
    "definition": "保险柜",
    "example": "The money is stored in the safe.",
    "example_trans": "钱存放在保险柜里。",
    "derivatives": [],
    "tags": ["安全", "储存"],
    "categories": ["银行"],
    "level": 1
  },
  {
    "word": "Vault",
    "phonetic": "/vɔːlt/",
    "definition": "金库",
    "example": "The vault is heavily guarded.",
    "example_trans": "金库戒备森严。",
    "derivatives": [],
    "tags": ["安全", "储存"],
    "categories": ["银行"],
    "level": 1
  },
  {
    "word": "Currency exchange",
    "phonetic": "/ˈkɜːrənsi ɪksˈtʃeɪndʒ/",
    "definition": "货币兑换",
    "example": "I need to go to the currency exchange to get euros.",
    "example_trans": "我需要去货币兑换处兑换欧元。",
    "derivatives": [],
    "tags": ["常用", "服务"],
    "categories": ["银行"],
    "level": 2
  },
  {
    "word": "Traveler's check",
    "phonetic": "/ˈtrævələrz tʃek/",
    "definition": "旅行支票",
    "example": "Traveler's checks are safer than carrying cash.",
    "example_trans": "旅行支票比携带现金更安全。",
    "derivatives": [],
    "tags": ["旅行", "支付"],
    "categories": ["银行"],
    "level": 2
  },
  {
    "word": "Cashier's check",
    "phonetic": "/kæˈʃɪrz tʃek/",
    "definition": "银行本票",
    "example": "I need a cashier's check for the down payment.",
    "example_trans": "我需要一张银行本票作为首付。",
    "derivatives": [],
    "tags": ["支付", "安全"],
    "categories": ["银行"],
    "level": 2
  },
  {
    "word": "Money order",
    "phonetic": "/ˈmʌni ˈɔːrdər/",
    "definition": "汇票",
    "example": "I sent a money order to my family.",
    "example_trans": "我给我的家人寄了一张汇票。",
    "derivatives": [],
    "tags": ["支付", "汇款"],
    "categories": ["银行"],
    "level": 2
  },
  {
    "word": "Payee",
    "phonetic": "/peɪˈiː/",
    "definition": "收款人",
    "example": "Write the payee's name on the check.",
    "example_trans": "在支票上写上收款人的名字。",
    "derivatives": [],
    "tags": ["支付", "信息"],
    "categories": ["银行"],
    "level": 2
  },
  {
    "word": "Payer",
    "phonetic": "/ˈpeɪər/",
    "definition": "付款人",
    "example": "The payer is responsible for the payment.",
    "example_trans": "付款人负责付款。",
    "derivatives": [],
    "tags": ["支付", "信息"],
    "categories": ["银行"],
    "level": 2
  },
  {
    "word": "Routing number",
    "phonetic": "/ˈraʊtɪŋ ˈnʌmbər/",
    "definition": "银行识别码",
    "example": "I need the routing number for the wire transfer.",
    "example_trans": "我需要电汇的银行识别码。",
    "derivatives": [],
    "tags": ["信息", "金融"],
    "categories": ["银行"],
    "level": 2
  },
  {
    "word": "Account number",
    "phonetic": "/əˈkaʊnt ˈnʌmbər/",
    "definition": "账号",
    "example": "Please provide your account number.",
    "example_trans": "请提供你的账号。",
    "derivatives": [],
    "tags": ["信息", "金融"],
    "categories": ["银行"],
    "level": 1
  },
  {
    "word": "Credit history",
    "phonetic": "/ˈkredɪt ˈhɪstəri/",
    "definition": "信用记录",
    "example": "Your credit history affects your ability to get a loan.",
    "example_trans": "你的信用记录会影响你获得贷款的能力。",
    "derivatives": [],
    "tags": ["金融", "信用"],
    "categories": ["银行"],
    "level": 2
  },
  {
    "word": "Annual percentage rate (APR)",
    "phonetic": "/ˈænjuəl pərˈsentɪdʒ reɪt/",
    "definition": "年利率",
    "example": "The APR on the credit card is very high.",
    "example_trans": "信用卡的年利率非常高。",
    "derivatives": [],
    "tags": ["金融", "利率"],
    "categories": ["银行"],
    "level": 3
  },
  {
    "word": "Compound interest",
    "phonetic": "/ˈkɑːmpaʊnd ˈɪntrəst/",
    "definition": "复利",
    "example": "Compound interest can help your savings grow faster.",
    "example_trans": "复利可以帮助你的储蓄更快地增长。",
    "derivatives": [],
    "tags": ["金融", "利率"],
    "categories": ["银行"],
    "level": 3
  },
  {
    "word": "Fixed interest rate",
    "phonetic": "/fɪkst ˈɪntrəst reɪt/",
    "definition": "固定利率",
    "example": "A fixed interest rate stays the same over the life of the loan.",
    "example_trans": "在贷款期限内，固定利率保持不变。",
    "derivatives": [],
    "tags": ["金融", "利率"],
    "categories": ["银行"],
    "level": 3
  },
  {
    "word": "Variable interest rate",
    "phonetic": "/ˈveriəbl ˈɪntrəst reɪt/",
    "definition": "浮动利率",
    "example": "A variable interest rate can change over time.",
    "example_trans": "浮动利率会随着时间变化。",
    "derivatives": [],
    "tags": ["金融", "利率"],
    "categories": ["银行"],
    "level": 3
  },
  {
    "word": "Principal",
    "phonetic": "/ˈprɪnsəpəl/",
    "definition": "本金",
    "example": "I need to pay down the principal on my loan.",
    "example_trans": "我需要偿还贷款的本金。",
    "derivatives": [],
    "tags": ["金融", "贷款"],
    "categories": ["银行"],
    "level": 2
  },
  {
    "word": "Term",
    "phonetic": "/tɜːrm/",
    "definition": "期限",
    "example": "What is the term of the loan?",
    "example_trans": "贷款的期限是多久？",
    "derivatives": [],
    "tags": ["金融", "贷款"],
    "categories": ["银行"],
    "level": 1
  },
  {
    "word": "Collateralized loan",
    "phonetic": "/kəˈlætərəlaɪzd loʊn/",
    "definition": "有抵押贷款",
    "example": "A mortgage is a type of collateralized loan.",
    "example_trans": "抵押贷款是一种有抵押贷款。",
    "derivatives": [],
    "tags": ["金融", "贷款"],
    "categories": ["银行"],
    "level": 3
  },
  {
    "word": "Unsecured loan",
    "phonetic": "/ˌʌnsɪˈkjʊrd loʊn/",
    "definition": "无抵押贷款",
    "example": "A credit card is a type of unsecured loan.",
    "example_trans": "信用卡是一种无抵押贷款。",
    "derivatives": [],
    "tags": ["金融", "贷款"],
    "categories": ["银行"],
    "level": 3
  },
  {
    "word": "Credit line",
    "phonetic": "/ˈkredɪt laɪn/",
    "definition": "信用额度",
    "example": "I need to increase my credit line.",
    "example_trans": "我需要提高我的信用额度。",
    "derivatives": [],
    "tags": ["金融", "信用"],
    "categories": ["银行"],
    "level": 2
  },
  {
    "word": "Minimum payment",
    "phonetic": "/ˈmɪnɪməm ˈpeɪmənt/",
    "definition": "最低还款额",
    "example": "I only paid the minimum payment on my credit card.",
    "example_trans": "我只支付了信用卡的最低还款额。",
    "derivatives": [],
    "tags": ["金融", "支付"],
    "categories": ["银行"],
    "level": 2
  },
  {
    "word": "Late fee",
    "phonetic": "/leɪt fiː/",
    "definition": "滞纳金",
    "example": "I was charged a late fee for paying the bill late.",
    "example_trans": "我因延迟支付账单而被收取了滞纳金。",
    "derivatives": [],
    "tags": ["费用", "支付"],
    "categories": ["银行"],
    "level": 2
  },
  {
    "word": "Grace period",
    "phonetic": "/ɡreɪs ˈpɪriəd/",
    "definition": "宽限期",
    "example": "The credit card has a grace period of 21 days.",
    "example_trans": "信用卡有21天的宽限期。",
    "derivatives": [],
    "tags": ["金融", "时间"],
    "categories": ["银行"],
    "level": 2
  },
  {
    "word": "Outstanding balance",
    "phonetic": "/aʊtˈstændɪŋ ˈbæləns/",
    "definition": "未偿余额",
    "example": "What is the outstanding balance on your credit card?",
    "example_trans": "你的信用卡未偿余额是多少？",
    "derivatives": [],
    "tags": ["金融", "余额"],
    "categories": ["银行"],
    "level": 2
  },
  {
    "word": "Credit bureau",
    "phonetic": "/ˈkredɪt ˈbjʊroʊ/",
    "definition": "信用局",
    "example": "The credit bureau collects information about your credit history.",
    "example_trans": "信用局收集关于你的信用记录的信息。",
    "derivatives": [],
    "tags": ["金融", "信用"],
    "categories": ["银行"],
    "level": 3
  },
  {
    "word": "Credit report",
    "phonetic": "/ˈkredɪt rɪˈpɔːrt/",
    "definition": "信用报告",
    "example": "I checked my credit report for errors.",
    "example_trans": "我检查了我的信用报告是否有错误。",
    "derivatives": [],
    "tags": ["金融", "信用"],
    "categories": ["银行"],
    "level": 2
  },
  {
    "word": "Dispute a charge",
    "phonetic": "/dɪˈspjuːt ə tʃɑːrdʒ/",
    "definition": "对费用提出异议",
    "example": "I need to dispute a charge on my credit card statement.",
    "example_trans": "我需要对我的信用卡账单上的一笔费用提出异议。",
    "derivatives": [],
    "tags": ["费用", "争议"],
    "categories": ["银行"],
    "level": 3
  },
  {
    "word": "Reconcile",
    "phonetic": "/ˈrekənsaɪl/",
    "definition": "核对",
    "example": "I need to reconcile my bank statement with my records.",
    "example_trans": "我需要将我的银行账单与我的记录进行核对。",
    "derivatives": [],
    "tags": ["金融", "记录"],
    "categories": ["银行"],
    "level": 3
  },
  {
    "word": "Direct debit",
    "phonetic": "/daɪˈrekt ˈdebɪt/",
    "definition": "直接扣款",
    "example": "I pay my bills by direct debit.",
    "example_trans": "我通过直接扣款支付账单。",
    "derivatives": [],
    "tags": ["支付", "自动"],
    "categories": ["银行"],
    "level": 2
  },
  {
    "word": "Standing order",
    "phonetic": "/ˈstændɪŋ ˈɔːrdər/",
    "definition": "定期付款指令",
    "example": "I set up a standing order to pay my rent.",
    "example_trans": "我设置了定期付款指令来支付我的租金。",
    "derivatives": [],
    "tags": ["支付", "自动"],
    "categories": ["银行"],
    "level": 3
  },
  {
    "word": "Remittance",
    "phonetic": "/rɪˈmɪtəns/",
    "definition": "汇款",
    "example": "I sent a remittance to my family overseas.",
    "example_trans": "我给我在海外的家人汇款。",
    "derivatives": [],
    "tags": ["支付", "国际"],
    "categories": ["银行"],
    "level": 2
  },
  {
    "word": "Beneficiary",
    "phonetic": "/ˌbenɪˈfɪʃieri/",
    "definition": "受益人",
    "example": "Who is the beneficiary of the account?",
    "example_trans": "谁是该账户的受益人？",
    "derivatives": [],
    "tags": ["金融", "法律"],
    "categories": ["银行"],
    "level": 3
  }
]
